json_config/__init__.py
json_config/_compat.py
json_config/contracts.py
json_config/main.py
json_config-2.0.1.dist-info/DESCRIPTION.rst
json_config-2.0.1.dist-info/METADATA
json_config-2.0.1.dist-info/RECORD
json_config-2.0.1.dist-info/WHEEL
json_config-2.0.1.dist-info/metadata.json
json_config-2.0.1.dist-info/top_level.txt
